{
  "ad-hoc-by-cherubino": {
    "done": true,
    "name": "Ad Hoc by Cherubino"
  },
  "after-hours-wine": {
    "done": true,
    "name": "After Hours Wine"
  },
  "altair-estate": {
    "done": true,
    "name": "Altair Estate"
  },
  "amato-vino": {
    "done": true,
    "name": "Amato Vino"
  },
  "amelia-park-wines": {
    "done": true,
    "name": "Amelia Park Wines"
  },
  "aravina-estate": {
    "done": true,
    "name": "Aravina Estate"
  },
  "barnyard1978": {
    "done": true,
    "name": "Barnyard1978"
  },
  "bettenays-margaret-river-wine-&-nougat": {
    "done": true,
    "name": "Bettenay Wines"
  },
  "borello-vineyards": {
    "done": true,
    "name": "Borello Vineyards"
  },
  "brown-hill-estate": {
    "done": true,
    "name": "Brown Hill Estate"
  },
  "cape-grace-wines": {
    "done": true,
    "name": "Cape Grace Wines"
  },
  "cape-mentelle": {
    "done": true,
    "name": "Cape Mentelle"
  },
  "cape-naturaliste-vineyard": {
    "done": true,
    "name": "Cape Naturaliste Vineyard "
  },
  "capel-vale-winery": {
    "done": true,
    "name": "Capel Vale Winery"
  },
  "cherubino-cellar-door-&-guesthouse": {
    "done": true,
    "name": "cherubino"
  },
  "churchview-estate": {
    "done": true,
    "name": "Churchview Estate"
  },
  "clairault-streicker": {
    "done": true,
    "name": "Clairault Streicker"
  },
  "coward-and-black-vineyards": {
    "done": true,
    "name": "Coward and Black Vineyards"
  },
  "credaro-family-estate": {
    "done": true,
    "name": "Credaro Family Estate"
  },
  "cullen-wines": {
    "done": true,
    "name": "Cullen Wines"
  },
  "deep-woods-estate": {
    "done": true,
    "name": "Deep Woods Estate"
  },
  "di-latte-estate": {
    "done": true,
    "name": "Di Latte Estate"
  },
  "domain-naturaliste": {
    "done": true,
    "name": "Domain Naturaliste"
  },
  "dormilona": {
    "done": true,
    "name": "Dormilona"
  },
  "driftwood-estate": {
    "done": true,
    "name": "Driftwood Estate"
  },
  "edwards-wines": {
    "done": true,
    "name": "Edwards Wines"
  },
  "evans-&-tate": {
    "done": true,
    "name": "Evans & Tate"
  },
  "evoi-wines": {
    "done": true,
    "name": "Evoi Wines"
  },
  "fermoy-estate": {
    "done": true,
    "name": "Fermoy Estate"
  },
  "firetail-wines": {
    "done": true,
    "name": "Firetail Wines"
  },
  "fishbone-wines": {
    "done": true,
    "name": "Fishbone Wines"
  },
  "flametree-wines": {
    "done": true,
    "name": "Flametree Wines"
  },
  "flowstone-wines": {
    "done": true,
    "name": "Flowstone Wines"
  },
  "fraser-gallop-estate": {
    "done": true,
    "name": "Fraser Gallop Estate"
  },
  "glenarty-road": {
    "done": true,
    "name": "Glenarty Road"
  },
  "goon-tycoons": {
    "done": true,
    "name": "Goon Tycoons"
  },
  "grace-farm": {
    "done": true,
    "name": "Grace Farm"
  },
  "gralyn-estate": {
    "done": true,
    "name": "Gralyn Estate"
  },
  "hamelin-bay-wines": {
    "done": true,
    "name": "Hamelin Bay Wines"
  },
  "happs-wine-&-commonage-pottery": {
    "done": true,
    "name": "Happs Wine"
  },
  "hay-shed-hill-wines": {
    "done": true,
    "name": "Hay Shed Hill Wines"
  },
  "house-of-cards-wine": {
    "done": true,
    "name": "House of Cards Wine"
  },
  "howard-park-wines": {
    "done": true,
    "name": "Howard Park Wines"
  },
  "jarvis-estate": {
    "done": true,
    "name": "Jarvis Estate"
  },
  "jilyara": {
    "done": true,
    "name": "Jilyara"
  },
  "juniper-wines": {
    "done": true,
    "name": "Juniper Wines"
  },
  "knotting-hill-estate": {
    "done": true,
    "name": "Knotting Hill Estate"
  },
  "las-vino": {
    "done": true,
    "name": "L.A.S. Vino"
  },
  "leeuwin-estate": {
    "done": true,
    "name": "Leeuwin Estate"
  },
  "lentedal-winery-&-wood-fired-pizza-cafe": {
    "done": true,
    "name": "Lentedal Vineyard Estate"
  },
  "lenton-brae": {
    "done": true,
    "name": "Lenton Brae"
  },
  "ls-merchants": {
    "done": true,
    "name": "LS Merchants"
  },
  "marq-wines": {
    "done": true,
    "name": "Marq Wines"
  },
  "mongrel-creek-wines-margaret-river": {
    "done": true,
    "name": "Mongrel Creek Wines"
  },
  "moss-wood": {
    "done": true,
    "name": "Moss Wood"
  },
  "mr-barval-fine-wines": {
    "done": true,
    "name": "Mr Barval "
  },
  "palmer-wine-cellar-door": {
    "done": true,
    "name": "Palmer Wine"
  },
  "passel-estate": {
    "done": true,
    "name": "Passel Estate"
  },
  "peacetree-wines": {
    "done": true,
    "name": "Peacetree Estate"
  },
  "pierro": {
    "done": true,
    "name": "Pierro"
  },
  "redgate-wines": {
    "done": true,
    "name": "Redgate Wines"
  },
  "rivendell-winery-estate": {
    "done": true,
    "name": "Rivendell Winery Estate"
  },
  "rosa-glen-farm": {
    "done": true,
    "name": "Rosa Glen Farm"
  },
  "rosily-vineyard": {
    "done": true,
    "name": "Rosily Vineyard"
  },
  "settlers-ridge-organic-wines": {
    "done": true,
    "name": "Settlers Ridge Organic Wines"
  },
  "si-vintners": {
    "done": true,
    "name": "Si Vintners"
  },
  "skigh-wine": {
    "done": true,
    "name": "Skigh Wine"
  },
  "snake-+-herring": {
    "done": true,
    "name": "Snake + Herring"
  },
  "south-by-south-west": {
    "done": true,
    "name": "South by South West"
  },
  "stella-bella-wines": {
    "done": true,
    "name": "Stella Bella Wines"
  },
  "stormflower-vineyard": {
    "done": true,
    "name": "Stormflower Vineyard"
  },
  "subsea-estate": {
    "done": true,
    "name": "Subsea Estate"
  },
  "swings-&-roundabouts": {
    "done": true,
    "name": "Swings & Roundabouts"
  },
  "the-berry-farm": {
    "done": true,
    "name": "The Berry Farm"
  },
  "the-valley-margaret-river": {
    "done": true,
    "name": "The Valley Margaret River"
  },
  "thompson-estate": {
    "done": true,
    "name": "Thompson Estate"
  },
  "vallée-du-venom---cellar-door": {
    "done": true,
    "name": "Vallée du Venom"
  },
  "vasse-felix": {
    "done": true,
    "name": "Vasse Felix"
  },
  "victory-point-wines": {
    "done": true,
    "name": "Victory Point Wines"
  },
  "voyager-estate": {
    "done": true,
    "name": "Voyager Estate"
  },
  "walsh-&-sons": {
    "done": true,
    "name": "Walsh & Sons"
  },
  "wayfinder-cellar-door-&-restaurant": {
    "done": true,
    "name": "Wayfinder "
  },
  "whicher-ridge-wines": {
    "done": true,
    "name": "Whicher Ridge Wines"
  },
  "willespie": {
    "done": true,
    "name": "Willespie"
  },
  "wills-domain": {
    "done": true,
    "name": "Wills Domain"
  },
  "windance-estate-wines": {
    "done": true,
    "name": "Windance Estate Wines"
  },
  "windows-estate": {
    "done": true,
    "name": "Windows Estate"
  },
  "wise-wine": {
    "done": true,
    "name": "Wise Wine"
  },
  "woody-nook-wines": {
    "done": true,
    "name": "Woody Nook Wines"
  },
  "xanadu-wines": {
    "done": true,
    "name": "Xanadu Wines"
  }
}